{
  "preRequisites:9": {
    "0:10": {
      "questIDHigh:4": -231857371118812213,
      "questIDLow:4": -5333711022391469539
    }
  },
  "properties:10": {
    "betterquesting:10": {
      "autoClaim:1": 0,
      "desc:8": "[quest]Large Solar Boiler[/quest]\n\nMachine Type: §aSolar Boiler§r\n\nDuring the day and with clear weather, the boiler will heat up at a rate of §c0.1%§r per second. \n\nDuring the night and rain, the boiler will cool at a rate of §c0.01%§r per second.\n\n[warn]Adding water to a dry boiler with a heat above 50% will cause it to explode![/warn]\n\nThe boiler needs a clear view of the sky in order to generate heat.\n\nTwo Tiers:\n\n§3Bronze§r: §a4800L/s§r of Steam at full heat.\n§3Steel§r: §a14400L/s§r of Steam at full heat.\n\nAfter §c24§r hours, the boiler will begin to calcify.\n\nMax calcification will occur after §c36§r hours, and steam output will be reduced to §a33.33%§r\n \nCalcification can be reset using the button in the GUI, and can be prevented by using §9Distilled§r water.\n\n§dQuest added by TheBigCheesish",
      "globalShare:1": 0,
      "icon:10": {
        "Count:3": 1,
        "Damage:2": 19076,
        "OreDict:8": "",
        "id:8": "gregtech:gt.blockmachines"
      },
      "isMain:1": 0,
      "isSilent:1": 0,
      "lockedProgress:1": 0,
      "name:8": "Large Solar Boiler",
      "questLogic:8": "AND",
      "repeatTime:3": -1,
      "repeat_relative:1": 1,
      "simultaneous:1": 0,
      "snd_complete:8": "random.levelup",
      "snd_update:8": "random.levelup",
      "taskLogic:8": "AND",
      "visibility:8": "NORMAL"
    }
  },
  "questIDHigh:4": -3198625678866431265,
  "questIDLow:4": -8467748140179403836,
  "rewards:9": {},
  "tasks:9": {
    "0:10": {
      "autoConsume:1": 0,
      "consume:1": 0,
      "groupDetect:1": 0,
      "ignoreNBT:1": 1,
      "index:3": 0,
      "partialMatch:1": 1,
      "requiredItems:9": {
        "0:10": {
          "Count:3": 1,
          "Damage:2": 19076,
          "OreDict:8": "",
          "id:8": "gregtech:gt.blockmachines"
        }
      },
      "taskID:8": "bq_standard:retrieval"
    }
  }
}